<annotation>
  <folder>VOC2007</folder>
  <filename>2020_09_15-Rillen_10x_0.30_6_Y2_X2_op5.png</filename>
  <source>
    <database>Coco database</database>
  </source>
  <size>
    <width>600</width>
    <height>600</height>
    <depth>3</depth>
  </size>
  <segmented>0</segmented>
  <object>
    <name>d</name>
    <pose>Unspecified</pose>
    <truncated>0</truncated>
    <difficult>0</difficult>
    <bndbox>
      <xmin>75</xmin>
      <ymin>320</ymin>
      <xmax>520</xmax>
      <ymax>539</ymax>
    </bndbox>
  </object>
  <object>
    <name>d</name>
    <pose>Unspecified</pose>
    <truncated>0</truncated>
    <difficult>0</difficult>
    <bndbox>
      <xmin>75</xmin>
      <ymin>0</ymin>
      <xmax>522</xmax>
      <ymax>99</ymax>
    </bndbox>
  </object>
  <object>
    <name>d</name>
    <pose>Unspecified</pose>
    <truncated>0</truncated>
    <difficult>0</difficult>
    <bndbox>
      <xmin>77</xmin>
      <ymin>143</ymin>
      <xmax>513</xmax>
      <ymax>343</ymax>
    </bndbox>
  </object>
  <object>
    <name>d</name>
    <pose>Unspecified</pose>
    <truncated>0</truncated>
    <difficult>0</difficult>
    <bndbox>
      <xmin>75</xmin>
      <ymin>498</ymin>
      <xmax>509</xmax>
      <ymax>599</ymax>
    </bndbox>
  </object>
</annotation>
